biasgen/__init__.py
biasgen/coil_setup.py
biasgen/config.py
biasgen/field_calc.py
biasgen/phantom.py
biasgen/typing_utils.py
biasgen/view_utils.py
biasgen-0.1.3.dist-info/LICENSE
biasgen-0.1.3.dist-info/METADATA
biasgen-0.1.3.dist-info/WHEEL
biasgen-0.1.3.dist-info/top_level.txt
biasgen-0.1.3.dist-info/RECORD
