Metadata-Version: 2.1
Name: biasgen
Version: 0.1.3
Summary: Utility functions to produce and visualize simulated bias fields generated according to Kern et. al's sinusoidal sensitivity model.
Home-page: https://github.com/lucianoAvinas/biasgen
Author: Luciano Vinas
Author-email: lucianovinas@g.ucla.edu
License: MIT
Requires-Python: >=3.10
License-File: LICENSE
Requires-Dist: numpy (>=1.20)
Requires-Dist: scipy
Requires-Dist: matplotlib
Provides-Extra: gpu
Requires-Dist: cupy-cuda11x ; extra == 'gpu'
